mkinx/How_To_Use_Mkinx.md
mkinx/Writing_Sphinx_Documentation.md
mkinx/__init__.py
mkinx/build.py
mkinx/commands.py
mkinx/conf.py
mkinx/documentation.md
mkinx/how_to_mkinx.md
mkinx/index.md
mkinx/material-icons.woff2
mkinx/material-style.css
mkinx/mkdocs.yml
mkinx/utils.py
mkinx/example_project/.DS_Store
mkinx/example_project/Makefile
mkinx/example_project/__init__.py
mkinx/example_project/__project__
mkinx/example_project/classif/__init__.py
mkinx/example_project/classif/ds.py
mkinx/example_project/classif/inference.py
mkinx/example_project/classif/models.py
mkinx/example_project/classif/__pycache__/__init__.cpython-36.pyc
mkinx/example_project/classif/__pycache__/ds.cpython-36.pyc
mkinx/example_project/classif/__pycache__/models.cpython-36.pyc
mkinx/example_project/datasets/__init__.py
mkinx/example_project/datasets/datasets.py
mkinx/example_project/datasets/__pycache__/__init__.cpython-36.pyc
mkinx/example_project/datasets/__pycache__/datasets.cpython-36.pyc
mkinx/example_project/matching/__init__.py
mkinx/example_project/matching/elastic.py
mkinx/example_project/matching/search.py
mkinx/example_project/matching/__pycache__/__init__.cpython-36.pyc
mkinx/example_project/matching/__pycache__/elastic.cpython-36.pyc
mkinx/example_project/matching/__pycache__/haha.cpython-36.pyc
mkinx/example_project/matching/__pycache__/module.cpython-36.pyc
mkinx/example_project/matching/__pycache__/search.cpython-36.pyc
mkinx/example_project/source/classif.rst
mkinx/example_project/source/conf.py
mkinx/example_project/source/datasets.rst
mkinx/example_project/source/example_project.classif.inference.rst
mkinx/example_project/source/example_project.classif.models.rst
mkinx/example_project/source/example_project.classif.rst
mkinx/example_project/source/example_project.datasets.datasets.rst
mkinx/example_project/source/example_project.datasets.rst
mkinx/example_project/source/example_project.matching.elastic.rst
mkinx-0.3.1.2.dist-info/METADATA
mkinx-0.3.1.2.dist-info/RECORD
mkinx-0.3.1.2.dist-info/WHEEL
mkinx-0.3.1.2.dist-info/top_level.txt
