Metadata-Version: 2.1
Name: mkinx
Version: 0.3.1.2
Summary: Manage sphinx documentations with mkdocs
Home-page: https://github.com/entrepreneur-interet-general/mkinx
Author: Victor Schmidt
Author-email: vsch@protonmail.com
License: GNU
Keywords: documentation doc sphinx mkdocs mkinx
Platform: UNKNOWN
Requires-Dist: watchdog
Requires-Dist: sphinx (>=1.7.6)
Requires-Dist: mkdocs
Requires-Dist: sphinx-rtd-theme (>=0.4.0)
Requires-Dist: mkdocs-material
Requires-Dist: pexpect
Requires-Dist: pygments
